cli_commands.py
db_utils.py
main.py
mcp_server.py
sqlctx-0.1.7.dist-info/LICENSE
sqlctx-0.1.7.dist-info/METADATA
sqlctx-0.1.7.dist-info/WHEEL
sqlctx-0.1.7.dist-info/entry_points.txt
sqlctx-0.1.7.dist-info/top_level.txt
sqlctx-0.1.7.dist-info/RECORD
