Metadata-Version: 2.1
Name: sqlctx
Version: 0.1.7
Summary: A tool for generating LLM context from database tables
Requires-Python: >=3.10
License-File: LICENSE
Requires-Dist: duckdb
Requires-Dist: pandas
Requires-Dist: pyyaml
Requires-Dist: psycopg2-binary
Requires-Dist: mysql-connector-python
Requires-Dist: fastmcp
Requires-Dist: uvicorn
Requires-Dist: toml>=0.10.2
Requires-Dist: click>=8.1.8
Requires-Dist: ruamel-yaml>=0.18.6
